pi_log/__init__.py
pi_log/logs.py
pi_log-0.5.8.1.dist-info/LICENSE
pi_log-0.5.8.1.dist-info/METADATA
pi_log-0.5.8.1.dist-info/WHEEL
pi_log-0.5.8.1.dist-info/RECORD
