Metadata-Version: 2.1
Name: pi-log
Version: 0.5.8.1
Summary: Project to add utility log functions for Python
License: MIT
Author: parnell
Author-email: 3028114+parnell@users.noreply.github.com
Requires-Python: >=3.9,<4.0
Classifier: License :: OSI Approved :: MIT License
Classifier: Programming Language :: Python :: 3
Classifier: Programming Language :: Python :: 3.9
Classifier: Programming Language :: Python :: 3.10
Classifier: Programming Language :: Python :: 3.11
Classifier: Programming Language :: Python :: 3.12
